s3lib/__init__.py
s3lib/ui.py
s3lib/utils.py
S3Lib-1.5.0.dist-info/METADATA
S3Lib-1.5.0.dist-info/WHEEL
S3Lib-1.5.0.dist-info/entry_points.txt
S3Lib-1.5.0.dist-info/top_level.txt
S3Lib-1.5.0.dist-info/RECORD
