Metadata-Version: 2.1
Name: S3Lib
Version: 1.5.0
Summary: Library and utilities for interfacing wtih S3
Home-page: http://pypi.python.org/pypi/S3Lib/
Author: Andrew Thomson
Author-email: athomsonguy@gmail.com
License: LICENSE.txt
Platform: UNKNOWN
Classifier: Development Status :: 5 - Production/Stable
Classifier: License :: OSI Approved :: MIT License
Classifier: Topic :: Software Development :: Libraries
Classifier: Programming Language :: Python :: 3.7
Classifier: Programming Language :: Python :: 2.7
Requires-Dist: safeoutput (>=2.0)
Requires-Dist: future
Requires-Dist: docopt
